.flake8
LICENSE
MANIFEST.in
README.md
requirements.txt
setup.py
order/__init__.py
order/__version__.py
order/analysis.py
order/category.py
order/config.py
order/dataset.py
order/mixins.py
order/process.py
order/shift.py
order/unique.py
order/util.py
order/variable.py
order.egg-info/PKG-INFO
order.egg-info/SOURCES.txt
order.egg-info/dependency_links.txt
order.egg-info/not-zip-safe
order.egg-info/requires.txt
order.egg-info/top_level.txt